p_talk_to_ai/__init__.py
p_talk_to_ai/p_talk_to_ai.py
p_talk_to_ai-2.0.dist-info/METADATA
p_talk_to_ai-2.0.dist-info/WHEEL
p_talk_to_ai-2.0.dist-info/top_level.txt
p_talk_to_ai-2.0.dist-info/RECORD
